{
    "title": "Ascendance of a Bookworm",
    "subtitle": "~ I would do anything to become a librarian ~",
    "books": [{
        "title": "Part I 🔒",
        "content": "part1-nav.json"
    }, {
        "title": "Part II 🔒",
        "content": "part2-nav.json"
    }, {
        "title": "Part III 🔒",
        "content": "part3-nav.json"
    }, {
        "title": "Part IV 🔒",
        "content": "part4-nav.json"
    }, {
        "title": "Part V",
        "content": "",
        "disabled": true
    }, {
        "title": "Side Stories 🔒",
        "content": "ss-nav.json"
    }, {
        "title": "Extra",
        "content": "extra-nav.json"
    }]
}